asc2csv/__init__.py
asc2csv/_version.py
asc2csv/converter.py
asc2csv-1.4.1.dist-info/LICENSE
asc2csv-1.4.1.dist-info/METADATA
asc2csv-1.4.1.dist-info/WHEEL
asc2csv-1.4.1.dist-info/entry_points.txt
asc2csv-1.4.1.dist-info/top_level.txt
asc2csv-1.4.1.dist-info/RECORD
