Metadata-Version: 2.1
Name: asc2csv
Version: 1.4.1
Summary: A Python package for converting EyeLink .asc files to structured .csv files.
Home-page: https://github.com/AhsanKhodami/asc2edf
Author: Mohammad Ahsan Khodami
Author-email: ahsan.khodami@gmail.com
Project-URL: Source, https://github.com/AhsanKhodami/asc2csv
Project-URL: Tracker, https://github.com/AhsanKhodami/asc2csv/issues
Classifier: Programming Language :: Python :: 3
Classifier: License :: OSI Approved :: MIT License
Classifier: Operating System :: OS Independent
Classifier: Intended Audience :: Science/Research
Classifier: Topic :: Scientific/Engineering :: Information Analysis
Requires-Python: >=3.6
License-File: LICENSE
Requires-Dist: pandas
